youtube_insight/__init__.py
youtube_insight/server.py
youtube_insight-0.1.0.dist-info/METADATA
youtube_insight-0.1.0.dist-info/WHEEL
youtube_insight-0.1.0.dist-info/entry_points.txt
youtube_insight-0.1.0.dist-info/licenses/LICENSE
youtube_insight-0.1.0.dist-info/RECORD
