Metadata-Version: 2.4
Name: youtube-insight
Version: 0.1.0
Summary: A practice project based on dabidstudio's YouTube Insights MCP Server.
Author-email: truestone <truestone@gmail.com>
License-Expression: MIT
License-File: LICENSE
Requires-Python: >=3.11
Requires-Dist: build>=1.2.2.post1
Requires-Dist: httpx>=0.28.1
Requires-Dist: mcp[cli]>=1.6.0
Requires-Dist: python-dotenv>=1.1.0
Requires-Dist: requests>=2.32.3
Requires-Dist: twine>=6.1.0
Requires-Dist: youtube-transcript-api>=1.0.3
